{
	"class": "DepictionTabView",
	"minVersion": "0.7",
	"tabs": [
		{
			"class": "DepictionStackView",
			"views": [
				{
					"class": "DepictionMarkdownView",
					"markdown": "This item is now Free.\n\nSee larger Screenshots below.."
				},
				{
					"class": "DepictionSeparatorView"
				},
				{
					"class": "DepictionScreenshotsView",
					"itemCornerRadius": 8,
					"itemSize": "{160, 160}",
					"screenshots": [
						{
							"url": "https://moreinfo.thebigboss.org/moreinfo/anisette1.jpg",
							"accessibilityText": ""
						},
						{
							"url": "https://moreinfo.thebigboss.org/moreinfo/anisette2.jpg",
							"accessibilityText": ""
						},
						{
							"url": "https://moreinfo.thebigboss.org/moreinfo/anisette3.jpg",
							"accessibilityText": ""
						},
						{
							"url": "https://moreinfo.thebigboss.org/moreinfo/anisette4.jpg",
							"accessibilityText": ""
						}
					]
				},
				{
					"class": "DepictionSeparatorView"
				},
				{
					"class": "DepictionTableTextView",
					"text": "February 5, 2018",
					"title": "Updated"
				},
				{
					"class": "DepictionTableTextView",
					"text": "Free Package",
					"title": "License"
				},
				{
					"class": "DepictionSeparatorView"
				}
			],
			"tabname": "Description"
		},
		{
			"class": "DepictionStackView",
			"views": [
				{
					"class": "DepictionSubheaderView",
					"title": "What's New",
					"useBoldText": true,
					"useBottomMargin": false
				},
				{
					"class": "DepictionSeparatorView"
				},
				{
					"class": "DepictionMarkdownView",
					"markdown": "This item is now Free.\n\n\n\nUpdate settings to remove bloat<br>\nFix iOS 10 issue<br>\n<br>\nAdd iOS 10 compatibility\n\nUI Fix for iOS 9.2<br>\n<p>\nFix crash when reordering favorites on iOS 9.3<br>\n<p>\nUI fix for iOS 9.3\n\nPreference refactor<br>\n<p>\nRemove rocketbootstrap dependency<br>\nImprove reorder favorites list controller<br>\n\nFix issue with FlipControlCenter alerts being hidden under Anisette\n\nAdd new support view in settings<br>\nFix issue with devices not auto-locking<br>\n<p>\nFavorite App reordering page displays app icon image and name instead of identifier.<br>\nFix issue on iOS 8 where the blur didn't show up when not using the textured mode.<Br>\n<br>\nChange toggle style to better indicate active state.<br>\n\n<p>\nAdd option to reorder favorite apps.<br>\nClean up leftover debugging calls<br>"
				}
			],
			"tabname": "Changes"
		}
	]
}