{
	"class": "DepictionTabView",
	"minVersion": "0.7",
	"tabs": [
		{
			"class": "DepictionStackView",
			"views": [
				{
					"class": "DepictionMarkdownView",
					"markdown": "Compatible with iOS 8, 9, 10, 11 and 12"
				},
				{
					"class": "DepictionSeparatorView"
				},
				{
					"class": "DepictionScreenshotsView",
					"itemCornerRadius": 8,
					"itemSize": "{160, 160}",
					"screenshots": [
						{
							"url": "https://moreinfo.thebigboss.org/moreinfo/calllogpro7-1.jpg",
							"accessibilityText": ""
						},
						{
							"url": "https://moreinfo.thebigboss.org/moreinfo/calllogpro7-2.jpg",
							"accessibilityText": ""
						},
						{
							"url": "https://moreinfo.thebigboss.org/moreinfo/calllogpro7-3.jpg",
							"accessibilityText": ""
						},
						{
							"url": "https://moreinfo.thebigboss.org/moreinfo/calllogpro7-4.jpg",
							"accessibilityText": ""
						}
					]
				},
				{
					"class": "DepictionSeparatorView"
				},
				{
					"class": "DepictionTableTextView",
					"text": "May 18, 2019",
					"title": "Updated"
				},
				{
					"class": "DepictionTableTextView",
					"text": "Commercial&nbsp;Package +&nbsp;Free&nbsp;Trial",
					"title": "License"
				},
				{
					"class": "DepictionTableTextView",
					"text": "$ 4.99",
					"title": "Suggested Price"
				},
				{
					"class": "DepictionSeparatorView"
				}
			],
			"tabname": "Description"
		},
		{
			"class": "DepictionStackView",
			"views": [
				{
					"class": "DepictionSubheaderView",
					"title": "What's New",
					"useBoldText": true,
					"useBottomMargin": false
				},
				{
					"class": "DepictionSeparatorView"
				},
				{
					"class": "DepictionMarkdownView",
					"markdown": "1. Added support for iOS 12 & A12 devices.\n2. Added 'Pull to Refresh' on mail calls screen - Use this feature sparingly and IF AND ONLY IF any calls are not logged by CallLogPro.\n\n\nCallLogPro needs latest RocketBootStrap from http://rpetri.ch/repo/. Please add this repo to your sources and install it.\n\n\n1. Added support for iOS 10.x.<br>\n2. Added support for iPhone 7 and 7 Plus.<br>\n3. New light weight and flat UI makes recent calls screen elegant.<br>\n4. Completely renovated and more organized settings.<br>\n5. Added support for new CallKit, i.e. CallLogPro manages all CallKit dependent apps, like Skype or WhatsApp in its history.<br>\n6. Support for 3D touch on both CallLogPro and MobilePhone apps.<br>\n<br>\nNote: After updating it might ask you to activate again, please do so. For contact pictures to be displayed on CallLogPro, you may need latest <a href=“cydia://package/com.iarrays.copic2” target=\"_new\">Copic 2</a><br>\n\nWhats New in 8.1.1:<br>\n========================<br>\n1. Added support for iOS 9<br>\n2. Added support for iPhone 6s and 6s Plus.<br>\n3. Added Force/3D Touch support (for devices < 6s, requires RevealMenu).<br>\n4. Added Automatic call backups feature.<br>\n5. Few enhancements and issue fixes.<br>\n\nChange Log 8.1:<Br>\n====================<Br>\n1. Added support for iOS 8.3 and 8.4<Br>\n2. Fixed frequent crashes on some devices.<Br>\n3. Fixed Phone app crash while trying to add a call when Replace Recents is turned on.<Br>\n4. When FaceTime call is received, CallLogPro is unable to identify the caller after respring. This issue is also fixed.<Br>\n5. Few other improvements and enhancements.<Br>"
				}
			],
			"tabname": "Changes"
		}
	]
}