{
	"class": "DepictionTabView",
	"minVersion": "0.7",
	"tabs": [
		{
			"class": "DepictionStackView",
			"views": [
				{
					"class": "DepictionMarkdownView",
					"markdown": "Compatible (specifically written) for iOS 10. Tested on iPhones 7 iOS 10.1.1.\n\nCCSmooth10 gives you visual and useful/functional options to make prettier/smoother/better the Sight and the Behavior of your Control Center.\n\nThe Tweak is out of Stage from my Repository, now with the adding of nice Features and Stuff like:\n\n- Make the Control Center Nice with the Translucent Blur Effect.\n\n- Make the Control Center Dark in the Background Backside View.\n\n- Make the Control Center Vertical in the Buttons and Toggles Layout (integration of my Tweak CCButtonsPlumb hosted on my Repository).\n\n- Make the Control Center Sharp in the Element's View.\n\n- Make the Control Center White in the Element's View.\n\nFeel free to contact me via Mail or via Twitter @CydiaGeek, enjoy it, thanks! :)\n\nConfigure options from Settings.\n\nCredits are on Preferences Panel.\n\nwould be greatly appreciated!"
				},
				{
					"class": "DepictionSeparatorView"
				},
				{
					"class": "DepictionScreenshotsView",
					"itemCornerRadius": 8,
					"itemSize": "{160, 160}",
					"screenshots": [
						{
							"url": "https://moreinfo.thebigboss.org/moreinfo/ccsmooth10-1.jpg",
							"accessibilityText": ""
						},
						{
							"url": "https://moreinfo.thebigboss.org/moreinfo/ccsmooth10-2.jpg",
							"accessibilityText": ""
						},
						{
							"url": "https://moreinfo.thebigboss.org/moreinfo/ccsmooth10-3.jpg",
							"accessibilityText": ""
						},
						{
							"url": "https://moreinfo.thebigboss.org/moreinfo/ccsmooth10-5.jpg",
							"accessibilityText": ""
						}
					]
				},
				{
					"class": "DepictionSeparatorView"
				},
				{
					"class": "DepictionTableTextView",
					"text": "February 26, 2018",
					"title": "Updated"
				},
				{
					"class": "DepictionTableTextView",
					"text": "Free Package",
					"title": "License"
				},
				{
					"class": "DepictionSeparatorView"
				}
			],
			"tabname": "Description"
		},
		{
			"class": "DepictionStackView",
			"views": [
				{
					"class": "DepictionSubheaderView",
					"title": "What's New",
					"useBoldText": true,
					"useBottomMargin": false
				},
				{
					"class": "DepictionSeparatorView"
				},
				{
					"class": "DepictionMarkdownView",
					"markdown": "Version 1.0.3\n- Added the option to Enable the Record Screen Shortcut Toggle on the Control Center.\n- Added the Label to Email Me in the Preferences Panel.\n- Change in Prefs Label.\n\n\nVersion 1.0.2<br>\n- Added the option to Enable the Power Mode Toggle on the Control Center.<br>\n- Fixes in the Preferences Labels Panel.<br>\n<Br>\nVersion 1.0.1-9<br>\n- Added the option to Make the Control Center No Scrolling Pages Animations Effect (tip by sinfool).<br>\n- Added the option to Make the Control Center No Scrolling Pages.<br>\n- Added the option to Disable the Touches On All Toggles and Shortcuts of the Control Center.<br>\n- Added the option to Make Switch On All Toggles and Shortcuts Images of the Control Center.<br>\n- Added the option to Make Square the Control Center Sections and Buttons (tip by prouser).<br>\n- Added the Label to Check Other Tweaks by Me on BigBoss Repo.<br>\nVersion 1.0.1-8<br>\n- Added the option to Make Make Gigantic the Control Center Logo Buttons (integration of CCAlien Tweak available on my Repo).<br>\n\nVersion 1.0.1-7<br>\n- Added the option to Hide the Media Controls of the Control Center leaving Still Functional (tip by prouser).<br>\n<br>\n<br>\nVersion 1.0.1-6<br>\n- Added the option to Hide All Toggles and Shortcuts of the Control Center.<br>\n- Added the option to Hide All Toggles and Shortcuts Images of the Control Center when they are turned Off.<br>\n- Added the option to Make Capsule the Control Center Buttons.<br>\nMerry Christmas! :-)<br>\n\nVersion 1.0.1-5<br>\n- Added the option to Enable the Native Control Center Mute Toggle (Code of EnableCCMute by iKilledAppl3).<br>\n\nVersion 1.0.1-4<br>\n- Added the option to Disable the Gesture to invoke the Control Center.<br>\n- Now you can add My Repo on Cydia and Donate me (thanks) with the New Labels in Preferences Panel.<br>\n\nVersion 1.0.1-3<br>\n- Added the option to Hide the Control Center Maximum Slider Icon (thanks immortal1s for the idea).<br>\n<br>\n<br>\nVersion 1.0.1-2<br>\n- Added the option to Hide the Control Center Bottom Page Dots (thanks @harrywantstodev for this Code).<br>\n- Added the option to Disable the Control Center Closing Effect.<br>\n- Small Changes in Preferences Orders.<br>"
				}
			],
			"tabname": "Changes"
		}
	]
}