{
	"class": "DepictionTabView",
	"minVersion": "0.7",
	"tabs": [
		{
			"class": "DepictionStackView",
			"views": [
				{
					"class": "DepictionMarkdownView",
					"markdown": "Giới thiệu HideJB, một tweak có chức năng bỏ qua phát hiện jailbreak trên các ứng dụng iOS.\n\nHideJB rất mạnh mẽ với nhiều lựa chọn:\n\nKhóa ứng dụng trong Sandbox (hộp cát)\nChế độ nguyên bản\nBộ lọc cơ bản\nBộ lọc nâng cao\nXây dựng bản đồ tệp tin\nNgoài ra HideJB còn có chế độ ForceTouch Nosub giúp bạn khởi chạy ứng dụng trong môi trường Safemode (tắt tweaks)\n\nCấu hình các tùy chọn bên trong ứng dụng Cài Đặt\n\n\n(ENG): Introducing HideJB, a tweak has the ability to skip jailbreak detection on iOS apps.\n\nHideJB is very powerful with many options:\n\nLock application in Sandbox (sandbox)\nOriginal mode\nBasic filter\nAdvanced filter\nBuild file map\nAlso HideJB has ForceTouch Nosub mode to help you launch apps in Safemode environment (turn off tweaks)\n\nConfigure options within the Settings application"
				},
				{
					"class": "DepictionSeparatorView"
				},
				{
					"class": "DepictionScreenshotsView",
					"itemCornerRadius": 8,
					"itemSize": "{160, 160}",
					"screenshots": [
						{
							"url": "https://moreinfo.thebigboss.org/moreinfo/hidejb1.jpg",
							"accessibilityText": ""
						},
						{
							"url": "https://moreinfo.thebigboss.org/moreinfo/hidejb2.jpg",
							"accessibilityText": ""
						},
						{
							"url": "https://moreinfo.thebigboss.org/moreinfo/hidejb3.jpg",
							"accessibilityText": ""
						},
						{
							"url": "https://moreinfo.thebigboss.org/moreinfo/hidejb4.jpg",
							"accessibilityText": ""
						}
					]
				},
				{
					"class": "DepictionSeparatorView"
				},
				{
					"class": "DepictionTableTextView",
					"text": "July 4, 2019",
					"title": "Updated"
				},
				{
					"class": "DepictionTableTextView",
					"text": "Free Package",
					"title": "License"
				},
				{
					"class": "DepictionSeparatorView"
				}
			],
			"tabname": "Description"
		},
		{
			"class": "DepictionStackView",
			"views": [
				{
					"class": "DepictionSubheaderView",
					"title": "What's New",
					"useBoldText": true,
					"useBottomMargin": false
				},
				{
					"class": "DepictionSeparatorView"
				},
				{
					"class": "DepictionMarkdownView",
					"markdown": "- Added iOS 9 support\n- Add Plus mode\n- Remove basic filters\n- Remove lock sandbox mode\n- Add Plus + mode\n- Fix bug, improve stability and support some applications"
				}
			],
			"tabname": "Changes"
		}
	]
}