{
	"class": "DepictionTabView",
	"minVersion": "0.7",
	"tabs": [
		{
			"class": "DepictionStackView",
			"views": [
				{
					"class": "DepictionMarkdownView",
					"markdown": ""
				},
				{
					"class": "DepictionSeparatorView"
				},
				{
					"class": "DepictionScreenshotsView",
					"itemCornerRadius": 8,
					"itemSize": "{160, 160}",
					"screenshots": [
						{
							"url": "https://moreinfo.thebigboss.org/moreinfo/keyhook1.jpg",
							"accessibilityText": ""
						},
						{
							"url": "https://moreinfo.thebigboss.org/moreinfo/keyhook2.jpg",
							"accessibilityText": ""
						}
					]
				},
				{
					"class": "DepictionSeparatorView"
				},
				{
					"class": "DepictionTableTextView",
					"text": "June 8, 2016",
					"title": "Updated"
				},
				{
					"class": "DepictionTableTextView",
					"text": "Commercial&nbsp;Package",
					"title": "License"
				},
				{
					"class": "DepictionTableTextView",
					"text": "$ 0.99",
					"title": "Suggested Price"
				},
				{
					"class": "DepictionSeparatorView"
				}
			],
			"tabname": "Description"
		},
		{
			"class": "DepictionStackView",
			"views": [
				{
					"class": "DepictionSubheaderView",
					"title": "What's New",
					"useBoldText": true,
					"useBottomMargin": false
				},
				{
					"class": "DepictionSeparatorView"
				},
				{
					"class": "DepictionMarkdownView",
					"markdown": "- Added options to change animation speed, timeout and appearance from settings\n- Alternative shortcuts to icons in the dock: ⌘ + q/w/e/... (for keyboards without a numbers row)\n- Added shortcut for deleting the selected app: ⌘ + ⇧ + d"
				}
			],
			"tabname": "Changes"
		}
	]
}