{
	"class": "DepictionTabView",
	"minVersion": "0.7",
	"tabs": [
		{
			"class": "DepictionStackView",
			"views": [
				{
					"class": "DepictionMarkdownView",
					"markdown": "Compatible with iOS 11\n\nNoMoreAppBar removes the annoying app bar from the bottom of the iMessage app!\n\nNo options to configure."
				},
				{
					"class": "DepictionSeparatorView"
				},
				{
					"class": "DepictionScreenshotsView",
					"itemCornerRadius": 8,
					"itemSize": "{160, 160}",
					"screenshots": [
						{
							"url": "https://moreinfo.thebigboss.org/moreinfo/nomoreappbar1.jpg",
							"accessibilityText": ""
						}
					]
				},
				{
					"class": "DepictionSeparatorView"
				},
				{
					"class": "DepictionTableTextView",
					"text": "April 24, 2018",
					"title": "Updated"
				},
				{
					"class": "DepictionTableTextView",
					"text": "Free Package",
					"title": "License"
				},
				{
					"class": "DepictionSeparatorView"
				}
			],
			"tabname": "Description"
		},
		{
			"class": "DepictionStackView",
			"views": [],
			"tabname": "Changes"
		}
	]
}