{
	"class": "DepictionTabView",
	"minVersion": "0.7",
	"tabs": [
		{
			"class": "DepictionStackView",
			"views": [
				{
					"class": "DepictionMarkdownView",
					"markdown": "Compatible with iOS 10.0 ~ 10.2. True Background fully fledged backgrounding manager tweak for iOS 10.\n\nUses: - Downloading or uploading files in the background.\n- Listening to video streams like Twitch in the background\n- And much more!\n\nConfigure options from Settings."
				},
				{
					"class": "DepictionSeparatorView"
				},
				{
					"class": "DepictionScreenshotsView",
					"itemCornerRadius": 8,
					"itemSize": "{160, 160}",
					"screenshots": [
						{
							"url": "https://moreinfo.thebigboss.org/moreinfo/truebackground1.jpg",
							"accessibilityText": ""
						}
					]
				},
				{
					"class": "DepictionSeparatorView"
				},
				{
					"class": "DepictionTableTextView",
					"text": "December 16, 2017",
					"title": "Updated"
				},
				{
					"class": "DepictionTableTextView",
					"text": "Commercial&nbsp;Package",
					"title": "License"
				},
				{
					"class": "DepictionTableTextView",
					"text": "$ 1.99",
					"title": "Suggested Price"
				},
				{
					"class": "DepictionSeparatorView"
				}
			],
			"tabname": "Description"
		},
		{
			"class": "DepictionStackView",
			"views": [],
			"tabname": "Changes"
		}
	]
}